<encryption xmlns="urn:oasis:names:tc:opendocument:xmlns:container" xmlns:enc="http://www.w3.org/2001/04/xmlenc#">
	<enc:EncryptedData>
		<enc:EncryptionMethod Algorithm="http://www.idpf.org/2008/embedding" />
		<enc:CipherData>
			<enc:CipherReference URI="OEBPS/font/Calibri-Bold.ttf" />
		</enc:CipherData>
	</enc:EncryptedData>
	<enc:EncryptedData>
		<enc:EncryptionMethod Algorithm="http://www.idpf.org/2008/embedding" />
		<enc:CipherData>
			<enc:CipherReference URI="OEBPS/font/Calibri-Italic.ttf" />
		</enc:CipherData>
	</enc:EncryptedData>
	<enc:EncryptedData>
		<enc:EncryptionMethod Algorithm="http://www.idpf.org/2008/embedding" />
		<enc:CipherData>
			<enc:CipherReference URI="OEBPS/font/Calibri.ttf" />
		</enc:CipherData>
	</enc:EncryptedData>
	<enc:EncryptedData>
		<enc:EncryptionMethod Algorithm="http://www.idpf.org/2008/embedding" />
		<enc:CipherData>
			<enc:CipherReference URI="OEBPS/font/HelveticaNeueLTPro-UltLt.otf" />
		</enc:CipherData>
	</enc:EncryptedData>
	<enc:EncryptedData>
		<enc:EncryptionMethod Algorithm="http://www.idpf.org/2008/embedding" />
		<enc:CipherData>
			<enc:CipherReference URI="OEBPS/font/SanFranciscoText-Bold.otf" />
		</enc:CipherData>
	</enc:EncryptedData>
	<enc:EncryptedData>
		<enc:EncryptionMethod Algorithm="http://www.idpf.org/2008/embedding" />
		<enc:CipherData>
			<enc:CipherReference URI="OEBPS/font/SanFranciscoText-Heavy.otf" />
		</enc:CipherData>
	</enc:EncryptedData>
	<enc:EncryptedData>
		<enc:EncryptionMethod Algorithm="http://www.idpf.org/2008/embedding" />
		<enc:CipherData>
			<enc:CipherReference URI="OEBPS/font/SanFranciscoText-Italic.otf" />
		</enc:CipherData>
	</enc:EncryptedData>
	<enc:EncryptedData>
		<enc:EncryptionMethod Algorithm="http://www.idpf.org/2008/embedding" />
		<enc:CipherData>
			<enc:CipherReference URI="OEBPS/font/SanFranciscoText-Light.otf" />
		</enc:CipherData>
	</enc:EncryptedData>
	<enc:EncryptedData>
		<enc:EncryptionMethod Algorithm="http://www.idpf.org/2008/embedding" />
		<enc:CipherData>
			<enc:CipherReference URI="OEBPS/font/SanFranciscoText-LightItalic.otf" />
		</enc:CipherData>
	</enc:EncryptedData>
	<enc:EncryptedData>
		<enc:EncryptionMethod Algorithm="http://www.idpf.org/2008/embedding" />
		<enc:CipherData>
			<enc:CipherReference URI="OEBPS/font/SanFranciscoText-Regular.otf" />
		</enc:CipherData>
	</enc:EncryptedData>
	<enc:EncryptedData>
		<enc:EncryptionMethod Algorithm="http://www.idpf.org/2008/embedding" />
		<enc:CipherData>
			<enc:CipherReference URI="OEBPS/font/TimesNewRomanPS-ItalicMT.ttf" />
		</enc:CipherData>
	</enc:EncryptedData>
</encryption>
